README.rst
setup.py
txttobitmap.py
txttobitmap.egg-info/PKG-INFO
txttobitmap.egg-info/SOURCES.txt
txttobitmap.egg-info/dependency_links.txt
txttobitmap.egg-info/entry_points.txt
txttobitmap.egg-info/requires.txt
txttobitmap.egg-info/top_level.txt