Metadata-Version: 1.1
Name: txttobitmap
Version: 1.0.1
Summary: Simple script that converts given file to a bitmap
Home-page: https://github.com/m4tx/txttobitmap
Author: Mateusz Maćkowski
Author-email: m4tx@m4tx.pl
License: MIT
Keywords: txt bitmap conversion
Platform: UNKNOWN
Classifier: Development Status :: 5 - Production/Stable
Classifier: Environment :: Console
Classifier: Intended Audience :: End Users/Desktop
Classifier: Topic :: Multimedia :: Graphics :: Graphics Conversion
Classifier: License :: OSI Approved :: MIT License
Classifier: Natural Language :: English
Classifier: Operating System :: OS Independent
Classifier: Programming Language :: Python :: 3
Classifier: Programming Language :: Python :: 3.2
Classifier: Programming Language :: Python :: 3.3
Classifier: Programming Language :: Python :: 3.4
Classifier: Programming Language :: Python :: 3.5
Classifier: Topic :: Utilities
